MANIFEST.in
setup.py
bin/biobox
biobox_cli/__init__.py
biobox_cli/behave_interface.py
biobox_cli/biobox_file.py
biobox_cli/biobox_helper.py
biobox_cli/container.py
biobox_cli/main.py
biobox_cli/version.py
biobox_cli.egg-info/PKG-INFO
biobox_cli.egg-info/SOURCES.txt
biobox_cli.egg-info/dependency_links.txt
biobox_cli.egg-info/requires.txt
biobox_cli.egg-info/top_level.txt
biobox_cli/assets/error_messages.yml
biobox_cli/assets/login_parameters.yml
biobox_cli/biobox_type/__init__.py
biobox_cli/biobox_type/assembler_benchmark.py
biobox_cli/biobox_type/profiling.py
biobox_cli/biobox_type/short_read_assembler.py
biobox_cli/command/__init__.py
biobox_cli/command/login.py
biobox_cli/command/run.py
biobox_cli/command/verify.py
biobox_cli/util/__init__.py
biobox_cli/util/assets.py
biobox_cli/util/error.py
biobox_cli/util/functional.py
biobox_cli/util/misc.py
biobox_cli/verification/__init__.py
biobox_cli/verification/__init__.pyc
biobox_cli/verification/assembler_benchmark.feature
biobox_cli/verification/assembler_read_based_benchmark.feature
biobox_cli/verification/environment.py
biobox_cli/verification/profiling.feature
biobox_cli/verification/profiling_benchmark.feature
biobox_cli/verification/short_read_assembler.feature
biobox_cli/verification/taxonomic_binning_benchmark.feature
biobox_cli/verification/__pycache__/__init__.cpython-34.pyc
biobox_cli/verification/data/assembler_benchmark/assembly.fasta
biobox_cli/verification/data/assembler_benchmark/references/reference.fasta
biobox_cli/verification/data/assembler_read_based_benchmark/assembly.fasta
biobox_cli/verification/data/assembler_read_based_benchmark/genome_paired_reads.fq.gz
biobox_cli/verification/data/profiling_benchmark/ground_truth.profile
biobox_cli/verification/data/profiling_benchmark/prediction.profile
biobox_cli/verification/data/short_read_assembler/genome_paired_reads.fq.gz
biobox_cli/verification/data/taxonomic_binning/contigs.fna
biobox_cli/verification/data/taxonomic_binning/labels.binning
biobox_cli/verification/data/taxonomic_binning/prediction.binning
biobox_cli/verification/data/taxonomic_binning/taxonomy/names.dmp
